[
  {
    "id": "proteccion-ejercicio-nivel-seguro-1",
    "groupId": "proteccion-nivel-seguro",
    "title": "Nivel Seguro - Jornada Laboral",
    "enunciado": "¿Cuál es el nivel de presión sonora máximo seguro para una jornada laboral de 8 horas?",
    "solution": {
      "steps": [
        "Datos: t = 8 horas",
        "Fórmula: L_seguro = 85 - 3 × log₂(t / 8)",
        "Sustitución: L_seguro = 85 - 3 × log₂(8 / 8)",
        "Cálculo: L_seguro = 85 - 3 × log₂(1) = 85 - 3 × 0",
        "Resultado: L_seguro = 85 dB"
      ],
      "result": "Para 8 horas de exposición, el límite seguro es 85 dB. Este es el estándar internacional de seguridad laboral."
    }
  },
  {
    "id": "proteccion-ejercicio-nivel-seguro-2",
    "groupId": "proteccion-nivel-seguro",
    "title": "Nivel Seguro - Concierto",
    "enunciado": "Si vas a estar en un concierto durante 2 horas, ¿cuál es el nivel máximo seguro sin protección?",
    "solution": {
      "steps": [
        "Datos: t = 2 horas",
        "Fórmula: L_seguro = 85 - 3 × log₂(t / 8)",
        "Sustitución: L_seguro = 85 - 3 × log₂(2 / 8)",
        "Cálculo: L_seguro = 85 - 3 × log₂(0.25) = 85 - 3 × (-2)",
        "Resultado: L_seguro = 85 + 6 = 91 dB"
      ],
      "result": "Para 2 horas, el nivel seguro es 91 dB. La mayoría de conciertos superan este nivel (95-110 dB), por eso se recomienda usar protección auditiva."
    }
  },
  {
    "id": "proteccion-ejercicio-tiempo-seguro-1",
    "groupId": "proteccion-tiempo-seguro",
    "title": "Tiempo Seguro - Discoteca",
    "enunciado": "Estás en una discoteca con 100 dB. ¿Cuánto tiempo puedes estar sin dañar tu audición?",
    "solution": {
      "steps": [
        "Datos: L = 100 dB",
        "Fórmula: t_seguro = 8 × 2^((85 - L) / 3)",
        "Sustitución: t_seguro = 8 × 2^((85 - 100) / 3)",
        "Cálculo: t_seguro = 8 × 2^(-15 / 3) = 8 × 2^(-5) = 8 × 0.03125",
        "Resultado: t_seguro = 0.25 h = 15 minutos"
      ],
      "result": "¡Solo 15 minutos! A 100 dB el riesgo de daño es muy alto. Usa tapones o toma descansos frecuentes saliendo fuera."
    }
  },
  {
    "id": "proteccion-ejercicio-tiempo-seguro-2",
    "groupId": "proteccion-tiempo-seguro",
    "title": "Tiempo Seguro - Cortadora de Césped",
    "enunciado": "Una cortadora de césped produce 91 dB. ¿Cuánto tiempo es seguro usarla sin protección?",
    "solution": {
      "steps": [
        "Datos: L = 91 dB",
        "Fórmula: t_seguro = 8 × 2^((85 - L) / 3)",
        "Sustitución: t_seguro = 8 × 2^((85 - 91) / 3)",
        "Cálculo: t_seguro = 8 × 2^(-6 / 3) = 8 × 2^(-2) = 8 × 0.25",
        "Resultado: t_seguro = 2 horas"
      ],
      "result": "Puedes usar la cortadora 2 horas sin protección. Si vas a tardar más, usa orejeras o tapones."
    }
  },
  {
    "id": "proteccion-ejercicio-dosis-1",
    "groupId": "proteccion-dosis-ruido",
    "title": "Dosis de Ruido - Concierto",
    "enunciado": "Asistes a un concierto de 3 horas con 105 dB. ¿Cuál es tu dosis de ruido?",
    "solution": {
      "steps": [
        "Datos: t = 3 h, L = 105 dB",
        "Primero calculamos tiempo seguro: t_seguro = 8 × 2^((85 - 105) / 3)",
        "t_seguro = 8 × 2^(-20/3) = 8 × 2^(-6.67) ≈ 0.079 h ≈ 4.7 minutos",
        "Fórmula dosis: D = (t / t_seguro) × 100%",
        "D = (3 / 0.079) × 100% = 3797%"
      ],
      "result": "¡Dosis de 3797%! Esto es casi 38 veces la dosis segura. Sin protección, este concierto causará daño auditivo. Con tapones de 25 dB, el nivel efectivo sería ~80 dB (seguro)."
    }
  },
  {
    "id": "proteccion-ejercicio-dosis-2",
    "groupId": "proteccion-dosis-ruido",
    "title": "Dosis de Ruido - Jornada Laboral",
    "enunciado": "Trabajas 8 horas en un ambiente de 88 dB. ¿Cuál es tu dosis de ruido diaria?",
    "solution": {
      "steps": [
        "Datos: t = 8 h, L = 88 dB",
        "Tiempo seguro: t_seguro = 8 × 2^((85 - 88) / 3)",
        "t_seguro = 8 × 2^(-1) = 8 × 0.5 = 4 horas",
        "Dosis: D = (8 / 4) × 100%",
        "D = 2 × 100% = 200%"
      ],
      "result": "Dosis del 200%, el doble de lo seguro. Debes usar protección auditiva obligatoriamente según normativa laboral."
    }
  },
  {
    "id": "proteccion-ejercicio-nivel-efectivo-1",
    "groupId": "proteccion-nivel-efectivo",
    "title": "Nivel Efectivo - Concierto con Tapones",
    "enunciado": "En un concierto de 105 dB usas tapones con NRR 25 dB. ¿Cuál es el nivel efectivo que llegas a tu oído?",
    "solution": {
      "steps": [
        "Datos: L_ambiente = 105 dB, NRR = 25 dB, tipo = tapones",
        "Para tapones: A_real = NRR - 7",
        "A_real = 25 - 7 = 18 dB",
        "L_efectivo = L_ambiente - A_real",
        "L_efectivo = 105 - 18 = 87 dB"
      ],
      "result": "Nivel efectivo de 87 dB. Aunque es ligeramente superior a 85 dB, para 2-3 horas es aceptable. Los tapones reducen significativamente el riesgo."
    }
  },
  {
    "id": "proteccion-ejercicio-nivel-efectivo-2",
    "groupId": "proteccion-nivel-efectivo",
    "title": "Nivel Efectivo - Construcción con Orejeras",
    "enunciado": "En una obra con 95 dB usas orejeras con NRR 30 dB. ¿Es suficiente protección?",
    "solution": {
      "steps": [
        "Datos: L_ambiente = 95 dB, NRR = 30 dB, tipo = orejeras",
        "Para orejeras: A_real = NRR - 3",
        "A_real = 30 - 3 = 27 dB",
        "L_efectivo = L_ambiente - A_real",
        "L_efectivo = 95 - 27 = 68 dB"
      ],
      "result": "Nivel efectivo de 68 dB, muy por debajo del límite de 85 dB. ¡Excelente protección! Puedes trabajar toda la jornada sin riesgo."
    }
  },
  {
    "id": "proteccion-ejercicio-atenuacion-1",
    "groupId": "proteccion-atenuacion-necesaria",
    "title": "Atenuación Necesaria - Discoteca",
    "enunciado": "Una discoteca tiene 110 dB. ¿Qué atenuación necesitas para reducirlo a 85 dB?",
    "solution": {
      "steps": [
        "Datos: L_ambiente = 110 dB, L_objetivo = 85 dB",
        "Fórmula: A_necesaria = L_ambiente - L_objetivo",
        "A_necesaria = 110 - 85",
        "A_necesaria = 25 dB"
      ],
      "result": "Necesitas 25 dB de atenuación. Recomendación: Tapones con filtro (20-25 dB) u orejeras básicas son suficientes."
    }
  },
  {
    "id": "proteccion-ejercicio-atenuacion-2",
    "groupId": "proteccion-atenuacion-necesaria",
    "title": "Atenuación Necesaria - Tiro Deportivo",
    "enunciado": "Un disparo produce 140 dB. ¿Qué protección necesitas?",
    "solution": {
      "steps": [
        "Datos: L_ambiente = 140 dB, L_objetivo = 85 dB",
        "A_necesaria = 140 - 85",
        "A_necesaria = 55 dB"
      ],
      "result": "Necesitas 55 dB de atenuación. ¡Protección doble obligatoria! Usa tapones (25 dB) + orejeras (30 dB) = 55 dB total. Nunca dispares sin protección."
    }
  },
  {
    "id": "proteccion-ejercicio-distancia-1",
    "groupId": "proteccion-distancia-segura",
    "title": "Distancia Segura - Altavoz de Concierto",
    "enunciado": "Un altavoz produce 120 dB a 1 metro. ¿A qué distancia es seguro (85 dB)?",
    "solution": {
      "steps": [
        "Datos: r₀ = 1 m, L₀ = 120 dB, L_seguro = 85 dB",
        "Fórmula: r = r₀ × 10^((L₀ - L_seguro) / 20)",
        "r = 1 × 10^((120 - 85) / 20)",
        "r = 1 × 10^(35 / 20) = 1 × 10^1.75",
        "r ≈ 56.2 m"
      ],
      "result": "Debes estar al menos a 56 metros del altavoz para que sea seguro sin protección. Por eso en conciertos siempre debes usar tapones, ¡es imposible estar tan lejos!"
    }
  },
  {
    "id": "proteccion-ejercicio-distancia-2",
    "groupId": "proteccion-distancia-segura",
    "title": "Distancia Segura - Motosierra",
    "enunciado": "Una motosierra produce 110 dB a 1 metro. ¿A qué distancia baja a 85 dB?",
    "solution": {
      "steps": [
        "Datos: r₀ = 1 m, L₀ = 110 dB, L_seguro = 85 dB",
        "r = 1 × 10^((110 - 85) / 20)",
        "r = 1 × 10^(25 / 20) = 1 × 10^1.25",
        "r ≈ 17.8 m"
      ],
      "result": "A 18 metros es seguro. Pero si estás usando la motosierra, ¡es imposible estar tan lejos! Siempre usa orejeras o tapones al operar herramientas ruidosas."
    }
  }
]
