[
  {
    "id": "fuerza_lorentz_carga_1",
    "groupId": "fuerza_lorentz_carga",
    "title": "Calcular Fuerza sobre Protón",
    "enunciado": "Un protón (q = 1.6e-19 C) se mueve a 2.5e6 m/s perpendicularmente (90°) a un campo magnético de 0.8 T. ¿Qué fuerza magnética experimenta?",
    "solution": {
      "steps": [
        "Datos: q = 1.6e-19 C, v = 2.5e6 m/s, B = 0.8 T, θ = 90°",
        "Fórmula: F = |q| v B sin(θ)",
        "Sustitución: F = |1.6e-19| * 2.5e6 * 0.8 * sin(90°)",
        "Resultado: F = 3.2e-13 N"
      ],
      "result": "3.2e-13 N"
    }
  },
  {
    "id": "fuerza_lorentz_carga_2",
    "groupId": "fuerza_lorentz_carga",
    "title": "Calcular Carga de una Partícula",
    "enunciado": "Una partícula experimenta una fuerza de 6.4e-13 N al moverse a 2.0e6 m/s en un campo magnético de 1.0 T, entrando con un ángulo de 90°. ¿Cuál es su carga?",
    "solution": {
      "steps": [
        "Datos: F = 6.4e-13 N, v = 2.0e6 m/s, B = 1.0 T, θ = 90°",
        "Fórmula: |q| = F / (v B sin(θ))",
        "Sustitución: |q| = 6.4e-13 / (2.0e6 * 1.0 * sin(90°))",
        "Resultado: |q| = 3.2e-19 C"
      ],
      "result": "3.2e-19 C"
    }
  },
  {
    "id": "fuerza_lorentz_carga_3",
    "groupId": "fuerza_lorentz_carga",
    "title": "Calcular Velocidad de una Partícula",
    "enunciado": "Una partícula con carga 3.2e-19 C experimenta una fuerza de 6.4e-13 N en un campo magnético de 1.0 T, entrando con un ángulo de 90°. ¿A qué velocidad se movía?",
    "solution": {
      "steps": [
        "Datos: F = 6.4e-13 N, q = 3.2e-19 C, B = 1.0 T, θ = 90°",
        "Fórmula: v = F / (|q| B sin(θ))",
        "Sustitución: v = 6.4e-13 / (|3.2e-19| * 1.0 * sin(90°))",
        "Resultado: v = 2.0e6 m/s"
      ],
      "result": "2.0e6 m/s"
    }
  },
    {
    "id": "fuerza_lorentz_carga_4",
    "groupId": "fuerza_lorentz_carga",
    "title": "Calcular Campo Magnético",
    "enunciado": "Una partícula con carga de 1.6e-19 C se mueve a 2.5e6 m/s y experimenta una fuerza de 3.2e-13 N al entrar perpendicularmente a un campo magnético. ¿Cuál es la magnitud del campo?",
    "solution": {
      "steps": [
        "Datos: q = 1.6e-19 C, v = 2.5e6 m/s, F = 3.2e-13 N, θ = 90°",
        "Fórmula: B = F / (|q| v sin(θ))",
        "Sustitución: B = 3.2e-13 / (|1.6e-19| * 2.5e6 * sin(90°))",
        "Resultado: B = 0.8 T"
      ],
      "result": "0.8 T"
    }
  },
  {
    "id": "fuerza_lorentz_conductor_1",
    "groupId": "fuerza_lorentz_conductor",
    "title": "Fuerza sobre un Cable",
    "enunciado": "Un cable de 1.5 m lleva una corriente de 10 A y forma un ángulo de 45° con un campo magnético de 0.2 T. ¿Cuál es la fuerza sobre el cable?",
    "solution": {
      "steps": [
        "Datos: I = 10 A, L = 1.5 m, B = 0.2 T, θ = 45°",
        "Fórmula: F = I L B sin(θ)",
        "Sustitución: F = 10 * 1.5 * 0.2 * sin(45°)",
        "Resultado: F = 2.12 N"
      ],
      "result": "2.12 N"
    }
  },
    {
    "id": "fuerza_lorentz_conductor_2",
    "groupId": "fuerza_lorentz_conductor",
    "title": "Calcular Corriente en un Cable",
    "enunciado": "Un cable de 2.0 m de longitud en un campo magnético de 0.5 T experimenta una fuerza de 1.5 N. Si el ángulo es de 90°, ¿qué corriente circula por él?",
    "solution": {
      "steps": [
        "Datos: F = 1.5 N, L = 2.0 m, B = 0.5 T, θ = 90°",
        "Fórmula: I = F / (L B sin(θ))",
        "Sustitución: I = 1.5 / (2.0 * 0.5 * sin(90°))",
        "Resultado: I = 1.5 A"
      ],
      "result": "1.5 A"
    }
  },
  {
    "id": "fuerza_lorentz_conductor_3",
    "groupId": "fuerza_lorentz_conductor",
    "title": "Calcular Longitud de un Cable",
    "enunciado": "Una corriente de 8 A circula por un cable que está a 30° en un campo de 0.25 T. Si la fuerza es de 1.2 N, ¿cuál es la longitud del cable?",
    "solution": {
      "steps": [
        "Datos: F = 1.2 N, I = 8 A, B = 0.25 T, θ = 30°",
        "Fórmula: L = F / (I B sin(θ))",
        "Sustitución: L = 1.2 / (8 * 0.25 * sin(30°))",
        "Resultado: L = 1.2 m"
      ],
      "result": "1.2 m"
    }
  },
  {
    "id": "fuerza_lorentz_conductor_4",
    "groupId": "fuerza_lorentz_conductor",
    "title": "Calcular Campo Magnético a partir de Fuerza",
    "enunciado": "Un alambre de 2.0 m de longitud conduce una corriente de 5 A y experimenta una fuerza de 0.1 N. Si está perpendicular al campo (90°), ¿cuál es la magnitud del campo magnético?",
    "solution": {
      "steps": [
        "Datos: F = 0.1 N, I = 5 A, L = 2.0 m, θ = 90°",
        "Fórmula: B = F / (I L sin(θ))",
        "Sustitución: B = 0.1 / (5 * 2.0 * sin(90°))",
        "Resultado: B = 0.01 T"
      ],
      "result": "0.01 T"
    }
  },
  {
    "id": "movimiento_circular_magnetico_1",
    "groupId": "movimiento_circular_magnetico",
    "title": "Radio de un Electrón",
    "enunciado": "Un electrón (m=9.11e-31 kg, q=1.6e-19 C) se mueve perpendicularmente a 2e6 m/s en un campo de 0.05 T. ¿Cuál es el radio de su trayectoria?",
    "solution": {
      "steps": [
        "Datos: m = 9.11e-31 kg, v = 2e6 m/s, q = 1.6e-19 C, B = 0.05 T",
        "Fórmula: r = (m v) / (|q| B)",
        "Sustitución: r = (9.11e-31 * 2e6) / (|1.6e-19| * 0.05)",
        "Resultado: r = 0.000228 m"
      ],
      "result": "0.228 mm"
    }
  },
    {
    "id": "movimiento_circular_magnetico_2",
    "groupId": "movimiento_circular_magnetico",
    "title": "Calcular Velocidad de una Partícula",
    "enunciado": "Un protón (m=1.67e-27 kg, q=1.6e-19 C) describe una órbita de 5 cm de radio en un campo magnético de 0.5 T. ¿Cuál es su velocidad?",
    "solution": {
      "steps": [
        "Datos: m = 1.67e-27 kg, q = 1.6e-19 C, r = 0.05 m, B = 0.5 T",
        "Fórmula: v = (r |q| B) / m",
        "Sustitución: v = (0.05 * |1.6e-19| * 0.5) / 1.67e-27",
        "Resultado: v = 2.395e6 m/s"
      ],
      "result": "2.4e6 m/s"
    }
  },
  {
    "id": "movimiento_circular_magnetico_3",
    "groupId": "movimiento_circular_magnetico",
    "title": "Calcular Carga de Partícula",
    "enunciado": "Una partícula de masa 6.64e-27 kg se mueve a 1.5e7 m/s en una trayectoria de 0.2 m de radio en un campo de 2.5 T. ¿Cuál es su carga?",
    "solution": {
      "steps": [
        "Datos: m = 6.64e-27 kg, v = 1.5e7 m/s, r = 0.2 m, B = 2.5 T",
        "Fórmula: |q| = (m v) / (r B)",
        "Sustitución: |q| = (6.64e-27 * 1.5e7) / (0.2 * 2.5)",
        "Resultado: |q| = 1.992e-19 C"
      ],
      "result": "1.99e-19 C"
    }
  },
    {
    "id": "movimiento_circular_magnetico_4",
    "groupId": "movimiento_circular_magnetico",
    "title": "Calcular Campo Magnético",
    "enunciado": "Un electrón (m=9.11e-31 kg, q=1.6e-19 C) se mueve a 3e6 m/s en una trayectoria de 0.1 m de radio. ¿Cuál es el campo magnético requerido?",
    "solution": {
      "steps": [
        "Datos: m = 9.11e-31 kg, v = 3e6 m/s, r = 0.1 m, q = 1.6e-19 C",
        "Fórmula: B = (m v) / (r |q|)",
        "Sustitución: B = (9.11e-31 * 3e6) / (0.1 * |1.6e-19|)",
        "Resultado: B = 0.00017 T"
      ],
      "result": "0.17 mT"
    }
  },
  {
    "id": "movimiento_circular_magnetico_5",
    "groupId": "movimiento_circular_magnetico",
    "title": "Calcular Masa de Partícula",
    "enunciado": "Una partícula de carga 1.6e-19 C se mueve a 1.5e6 m/s en un campo de 0.7 T, describiendo un círculo de 3.2 cm de radio. ¿Cuál es su masa?",
    "solution": {
      "steps": [
        "Datos: r = 0.032 m, q = 1.6e-19 C, v = 1.5e6 m/s, B = 0.7 T",
        "Fórmula: m = (r |q| B) / v",
        "Sustitución: m = (0.032 * |1.6e-19| * 0.7) / 1.5e6",
        "Resultado: m = 2.389e-27 kg"
      ],
      "result": "2.39e-27 kg"
    }
  },
  {
    "id": "momento_dipolar_magnetico_1",
    "groupId": "momento_dipolar_magnetico",
    "title": "Momento Dipolar de una Bobina",
    "enunciado": "Una bobina de 150 vueltas y 10 cm² de área lleva una corriente de 0.5 A. ¿Cuál es su momento dipolar magnético?",
    "solution": {
      "steps": [
        "Datos: N = 150, I = 0.5 A, A = 0.001 m²",
        "Fórmula: μ = N I A",
        "Sustitución: μ = 150 * 0.5 * 0.001",
        "Resultado: μ = 0.075 A·m²"
      ],
      "result": "0.075 A·m²"
    }
  },
    {
    "id": "momento_dipolar_magnetico_2",
    "groupId": "momento_dipolar_magnetico",
    "title": "Calcular Número de Vueltas",
    "enunciado": "Una bobina con área de 0.02 m² y corriente de 2 A tiene un momento dipolar de 5 A·m². ¿Cuántas vueltas tiene?",
    "solution": {
      "steps": [
        "Datos: μ = 5 A·m², I = 2 A, A = 0.02 m²",
        "Fórmula: N = μ / (I A)",
        "Sustitución: N = 5 / (2 * 0.02)",
        "Resultado: N = 125"
      ],
      "result": "125 vueltas"
    }
  },
  {
    "id": "momento_dipolar_magnetico_3",
    "groupId": "momento_dipolar_magnetico",
    "title": "Calcular Corriente de una Espira",
    "enunciado": "Una espira circular de 50 vueltas y 5 cm de radio (Área = πr²) tiene un momento dipolar magnético de 0.1 A·m². ¿Qué corriente circula por ella?",
    "solution": {
      "steps": [
        "Primero, calcular el área: A = π * (0.05 m)² ≈ 0.00785 m²",
        "Datos: μ = 0.1 A·m², N = 50, A = 0.00785 m²",
        "Fórmula: I = μ / (N A)",
        "Sustitución: I = 0.1 / (50 * 0.00785)",
        "Resultado: I = 0.255 A"
      ],
      "result": "0.255 A"
    }
  },
  {
    "id": "momento_dipolar_magnetico_4",
    "groupId": "momento_dipolar_magnetico",
    "title": "Calcular Área de una Bobina",
    "enunciado": "Una bobina de 200 vueltas con una corriente de 1.5 A tiene un momento dipolar de 3 A·m². ¿Cuál es el área de la bobina?",
    "solution": {
      "steps": [
        "Datos: μ = 3 A·m², N = 200, I = 1.5 A",
        "Fórmula: A = μ / (N I)",
        "Sustitución: A = 3 / (200 * 1.5)",
        "Resultado: A = 0.01 m²"
      ],
      "result": "0.01 m²"
    }
  },
  {
    "id": "torque_magnetico_1",
    "groupId": "torque_magnetico",
    "title": "Torque sobre una Bobina",
    "enunciado": "Una bobina con un momento dipolar de 1.5 A·m² está en un campo de 0.8 T. Si el ángulo entre el momento dipolar y el campo es de 30°, ¿cuál es el torque que experimenta?",
    "solution": {
      "steps": [
        "Datos: μ = 1.5 A·m², B = 0.8 T, θ = 30°",
        "Fórmula: τ = μ B sin(θ)",
        "Sustitución: τ = 1.5 * 0.8 * sin(30°)",
        "Resultado: τ = 0.6 N·m"
      ],
      "result": "0.6 N·m"
    }
  },
  {
    "id": "torque_magnetico_2",
    "groupId": "torque_magnetico",
    "title": "Calcular Momento Dipolar desde Torque",
    "enunciado": "Una espira experimenta un torque máximo de 1.2 N·m (cuando θ=90°) en un campo magnético de 1.5 T. ¿Cuál es el momento dipolar magnético de la espira?",
    "solution": {
      "steps": [
        "Datos: τ = 1.2 N·m, B = 1.5 T, θ = 90°",
        "Fórmula: μ = τ / (B sin(θ))",
        "Sustitución: μ = 1.2 / (1.5 * sin(90°))",
        "Resultado: μ = 0.8 A·m²"
      ],
      "result": "0.8 A·m²"
    }
  },
    {
    "id": "torque_magnetico_3",
    "groupId": "torque_magnetico",
    "title": "Calcular Campo Magnético desde Torque",
    "enunciado": "Una bobina con momento dipolar de 2.0 A·m² experimenta un torque de 0.5 N·m cuando está a 30° en un campo magnético. ¿Cuál es la fuerza del campo?",
    "solution": {
      "steps": [
        "Datos: τ = 0.5 N·m, μ = 2.0 A·m², θ = 30°",
        "Fórmula: B = τ / (μ sin(θ))",
        "Sustitución: B = 0.5 / (2.0 * sin(30°))",
        "Resultado: B = 0.5 T"
      ],
      "result": "0.5 T"
    }
  },
  {
    "id": "energia_potencial_magnetica_1",
    "groupId": "energia_potencial_magnetica",
    "title": "Energía Potencial de una Bobina",
    "enunciado": "Calcula la energía potencial de una bobina con μ = 2 A·m² en un campo de 0.5 T, cuando el ángulo entre el momento dipolar y el campo es de 60°.",
    "solution": {
      "steps": [
        "Datos: μ = 2 A·m², B = 0.5 T, θ = 60°",
        "Fórmula: U = -μ B cos(θ)",
        "Sustitución: U = -2 * 0.5 * cos(60°)",
        "Resultado: U = -0.5 J"
      ],
      "result": "-0.5 J"
    }
  },
  {
    "id": "energia_potencial_magnetica_2",
    "groupId": "energia_potencial_magnetica",
    "title": "Calcular Momento Dipolar desde Energía",
    "enunciado": "Una bobina tiene una energía potencial de -1.2 J cuando está a 45° en un campo magnético de 2.0 T. ¿Cuál es su momento dipolar?",
    "solution": {
      "steps": [
        "Datos: U = -1.2 J, B = 2.0 T, θ = 45°",
        "Fórmula: μ = -U / (B cos(θ))",
        "Sustitución: μ = -(-1.2) / (2.0 * cos(45°))",
        "Resultado: μ = 0.8485 A·m²"
      ],
      "result": "0.85 A·m²"
    }
  },
  {
    "id": "energia_potencial_magnetica_3",
    "groupId": "energia_potencial_magnetica",
    "title": "Calcular Campo Magnético desde Energía",
    "enunciado": "Una espira con momento dipolar de 2.5 A·m² tiene una energía potencial de -3.0 J cuando está alineada con el campo (cos(0°)=1). ¿Cuál es la magnitud del campo magnético?",
    "solution": {
      "steps": [
        "Datos: U = -3.0 J, μ = 2.5 A·m², θ = 0°",
        "Fórmula: B = -U / (μ cos(θ))",
        "Sustitución: B = -(-3.0) / (2.5 * cos(0°))",
        "Resultado: B = 1.2 T"
      ],
      "result": "1.2 T"
    }
  }
]