[
  {
    "id": "global-ejercicio-01",
    "groupId": "ciclo_de_rankine_con_turbina_de_gas-grupo-1",
    "title": "Eficiencia Global de Sistema",
    "enunciado": "Un sistema produce 200 MW eléctricos + 150 MW térmicos útiles, consumiendo 400 MW totales. Calcula eficiencia global.",
    "solution": {
      "steps": [
        "Datos: W_total = 200 MW, Q_util = 150 MW, Q_entrada = 400 MW",
        "Fórmula: η_global = (W_total + Q_util) / Q_entrada",
        "Sustitución: η_global = (200 + 150) / 400",
        "η_global = 350 / 400 = 0.875 = 87.5%"
      ],
      "result": "87.5%"
    }
  },
  {
    "id": "global-ejercicio-02",
    "groupId": "ciclo_de_rankine_con_turbina_de_gas-grupo-1",
    "title": "Factor de Capacidad",
    "enunciado": "Una planta de 100 MW produjo 700000 MWh en un año (8760 horas). Calcula el factor de capacidad.",
    "solution": {
      "steps": [
        "Datos: Capacidad = 100 MW, Tiempo = 8760 h/año",
        "E_máxima = 100 MW × 8760 h = 876000 MWh/año",
        "E_real = 700000 MWh/año",
        "Fórmula: FC = E_real / E_máxima",
        "FC = 700000 / 876000 = 0.799 = 79.9%"
      ],
      "result": "79.9%"
    }
  }
]
