[
  {
    "id": "conveccion-ejercicio-01",
    "groupId": "conveccion-grupo-1",
    "title": "Convección Forzada",
    "enunciado": "Una placa de 0.5 m² a 80°C se enfría por aire a 20°C con h=50 W/(m²·K). Calcula el flujo de calor.",
    "solution": {
      "steps": [
        "Datos: h = 50 W/(m²·K), A = 0.5 m², T_s = 80°C, T_∞ = 20°C",
        "ΔT = 80 - 20 = 60 K",
        "Fórmula: Q = h × A × ΔT",
        "Q = 50 × 0.5 × 60",
        "Q = 1500 W"
      ],
      "result": "1500 W"
    }
  },
  {
    "id": "conveccion-ejercicio-02",
    "groupId": "conveccion-grupo-1",
    "title": "Resistencia por Convección",
    "enunciado": "Calcula la resistencia térmica por convección con h=100 W/(m²·K) y A=2 m².",
    "solution": {
      "steps": [
        "Datos: h = 100 W/(m²·K), A = 2 m²",
        "Fórmula: R_conv = 1 / (h × A)",
        "R_conv = 1 / (100 × 2)",
        "R_conv = 0.005 K/W"
      ],
      "result": "0.005 K/W"
    }
  },
  {
    "id": "coeficiente-h-ejercicio-01",
    "groupId": "conveccion-grupo-2",
    "title": "Cálculo del coeficiente de convección",
    "enunciado": "Un intercambiador transfiere Q = 2000 W a través de un área de 4 m², con T_s = 60°C y T_∞ = 30°C. Calcula el coeficiente de convección h.",
    "solution": {
      "steps": [
        "Datos: Q = 2000 W, A = 4 m², T_s = 60°C, T_∞ = 30°C",
        "ΔT = 60 - 30 = 30 K",
        "Fórmula: h = Q / [A × ΔT]",
        "h = 2000 / (4 × 30)",
        "h = 16.67 W/(m²·K)"
      ],
      "result": "16.67 W/(m²·K)"
    }
  }
]
