[
  {
    "id": "manos_mojadas",
    "groupId": "prevencion_accidentes",
    "title": "Regla de oro: manos secas",
    "enunciado": "¿Por qué nunca debes tocar aparatos eléctricos con las manos mojadas?",
    "solution": {
      "steps": [
        "El agua reduce drásticamente la resistencia de la piel:",
        "",
        "PIEL SECA:",
        "• Resistencia: 100,000 Ω",
        "• Corriente a 230V: I = 230/100,000 = 2.3 mA",
        "• Resultado: Cosquilleo, no peligroso",
        "",
        "PIEL MOJADA:",
        "• Resistencia: 1,000 Ω (100 veces menos)",
        "• Corriente a 230V: I = 230/1,000 = 230 mA",
        "• Resultado: MORTAL (fibrilación ventricular)",
        "",
        "DIFERENCIA: 100 veces más corriente",
        "",
        "REGLA DE ORO:",
        "✅ Siempre sécate las manos antes de tocar electricidad",
        "✅ No uses aparatos eléctricos en el baño",
        "✅ Mantén aparatos alejados del agua"
      ],
      "result": "El agua reduce la resistencia 100 veces, aumentando la corriente letal"
    }
  },
  {
    "id": "sobrecarga_enchufe",
    "groupId": "prevencion_accidentes",
    "title": "Evitar sobrecarga de enchufes",
    "enunciado": "Tienes una regleta de 10 A. ¿Puedes conectar: TV (200W), ordenador (500W), calefactor (2000W) y microondas (1000W)?",
    "solution": {
      "steps": [
        "Calcular la corriente total:",
        "",
        "Potencia total: 200 + 500 + 2000 + 1000 = 3700 W",
        "Corriente: I = P / V = 3700 / 230 = 16.1 A",
        "",
        "Límite de la regleta: 10 A",
        "",
        "16.1 A > 10 A → ¡SOBRECARGA!",
        "",
        "PELIGROS:",
        "• Los cables se calientan",
        "• Puede fundir el aislamiento",
        "• Riesgo de incendio",
        "• Puede saltar el magnetotérmico",
        "",
        "SOLUCIÓN:",
        "• Usar varios enchufes diferentes",
        "• No conectar el calefactor y microondas juntos",
        "• Usar regleta de mayor capacidad (16 A)",
        "",
        "❌ NO conectar todos a la vez"
      ],
      "result": "NO, 16.1 A supera el límite de 10 A → Riesgo de incendio"
    }
  },
  {
    "id": "cables_deteriorados",
    "groupId": "prevencion_accidentes",
    "title": "Cables pelados o deteriorados",
    "enunciado": "¿Qué hacer si encuentras un cable con el aislamiento roto?",
    "solution": {
      "steps": [
        "PELIGROS de cables deteriorados:",
        "• Contacto directo con conductor (230V)",
        "• Riesgo de electrocución",
        "• Cortocircuitos y chispas",
        "• Riesgo de incendio",
        "",
        "QUÉ HACER:",
        "",
        "1. NO TOCAR el cable",
        "2. DESCONECTAR el aparato de la corriente",
        "3. EVALUAR el daño:",
        "   • Si es pequeño: reparar con cinta aislante",
        "   • Si es grande: REEMPLAZAR el cable completo",
        "",
        "4. Si no sabes repararlo: llamar a electricista",
        "",
        "PREVENCIÓN:",
        "✅ Revisar cables periódicamente",
        "✅ No doblar cables en ángulos cerrados",
        "✅ No pasar cables bajo alfombras",
        "✅ No tirar del cable para desenchufar",
        "✅ Proteger cables de mascotas y niños"
      ],
      "result": "Desconectar, no tocar, reparar o reemplazar según el daño"
    }
  },
  {
    "id": "protectores_infantiles",
    "groupId": "prevencion_accidentes",
    "title": "Protección infantil",
    "enunciado": "¿Por qué son importantes los protectores de enchufes si hay niños en casa?",
    "solution": {
      "steps": [
        "Los niños pequeños son especialmente vulnerables:",
        "",
        "RIESGOS:",
        "• Curiosidad natural por explorar",
        "• Introducen objetos metálicos en enchufes",
        "• No comprenden el peligro",
        "• Su cuerpo tiene menor resistencia",
        "• Corrientes menores son más peligrosas",
        "",
        "PROTECTORES DE ENCHUFES:",
        "• Tapan los agujeros del enchufe",
        "• Impiden introducir objetos",
        "• Fáciles de instalar",
        "• Económicos (0.50-1 € cada uno)",
        "",
        "OTRAS MEDIDAS:",
        "✅ Enchufes con obturador (estándar europeo)",
        "✅ Regletas con tapa de seguridad",
        "✅ Educar a los niños sobre el peligro",
        "✅ Supervisión constante",
        "",
        "IMPORTANTE: Los enchufes modernos Schuko tienen obturadores,",
        "pero los protectores añaden seguridad extra"
      ],
      "result": "Impiden que niños introduzcan objetos en enchufes, evitando electrocución"
    }
  },
  {
    "id": "herramientas_aisladas",
    "groupId": "prevencion_accidentes",
    "title": "Herramientas aisladas",
    "enunciado": "¿Por qué los electricistas usan herramientas con mango aislado?",
    "solution": {
      "steps": [
        "Las herramientas aisladas protegen al electricista:",
        "",
        "FUNCIONAMIENTO:",
        "• Mango de plástico o goma (aislante)",
        "• Impide el paso de corriente al cuerpo",
        "• Certificadas hasta 1000V",
        "• Color naranja o amarillo (identificación)",
        "",
        "EJEMPLO DE PROTECCIÓN:",
        "Si tocas accidentalmente un cable con tensión:",
        "• Con herramienta normal: corriente pasa a tu cuerpo",
        "• Con herramienta aislada: corriente NO pasa",
        "",
        "HERRAMIENTAS QUE DEBEN SER AISLADAS:",
        "✅ Destornilladores",
        "✅ Alicates",
        "✅ Pelacables",
        "✅ Llaves",
        "✅ Comprobadores de tensión",
        "",
        "IMPORTANTE:",
        "• Revisar el aislamiento regularmente",
        "• No usar si está dañado",
        "• Limpiar y mantener en buen estado",
        "",
        "❌ NUNCA usar herramientas metálicas sin aislamiento"
      ],
      "result": "El aislamiento impide que la corriente pase al cuerpo del electricista"
    }
  },
  {
    "id": "desconectar_antes_limpiar",
    "groupId": "prevencion_accidentes",
    "title": "Desconectar antes de limpiar",
    "enunciado": "¿Por qué debes desenchufar un aparato antes de limpiarlo?",
    "solution": {
      "steps": [
        "Limpiar aparatos conectados es muy peligroso:",
        "",
        "RIESGOS:",
        "1. AGUA Y ELECTRICIDAD:",
        "   • Productos de limpieza contienen agua",
        "   • El agua conduce la electricidad",
        "   • Puede entrar en el aparato",
        "",
        "2. CONTACTO ACCIDENTAL:",
        "   • Puedes tocar partes con tensión",
        "   • Especialmente si el aparato está abierto",
        "",
        "3. CORTOCIRCUITO:",
        "   • Líquidos pueden causar cortocircuitos internos",
        "   • Daño permanente al aparato",
        "   • Riesgo de incendio",
        "",
        "PROCEDIMIENTO CORRECTO:",
        "1. ✅ DESENCHUFAR el aparato",
        "2. ✅ ESPERAR a que se enfríe (si estaba caliente)",
        "3. ✅ LIMPIAR con paño húmedo (no mojado)",
        "4. ✅ SECAR completamente",
        "5. ✅ ESPERAR 10 minutos antes de enchufar",
        "",
        "NUNCA limpiar con el aparato enchufado"
      ],
      "result": "Evita electrocución, cortocircuitos y daños al aparato"
    }
  },
  {
    "id": "extension_exterior",
    "groupId": "prevencion_accidentes",
    "title": "Cables de extensión en exterior",
    "enunciado": "¿Qué precauciones debes tomar al usar un alargador en el jardín?",
    "solution": {
      "steps": [
        "Usar electricidad en exteriores requiere precauciones especiales:",
        "",
        "RIESGOS ADICIONALES:",
        "• Lluvia y humedad",
        "• Contacto con tierra húmeda",
        "• Exposición al sol (deterioro del aislamiento)",
        "• Pisotones y daños mecánicos",
        "",
        "PRECAUCIONES OBLIGATORIAS:",
        "",
        "1. USAR ALARGADOR APROPIADO:",
        "   ✅ Certificado para uso exterior (IP44 o superior)",
        "   ✅ Con toma de tierra",
        "   ✅ Cable grueso (mínimo 1.5 mm²)",
        "",
        "2. PROTECCIÓN:",
        "   ✅ Mantener conexiones elevadas (no en el suelo)",
        "   ✅ Proteger de la lluvia",
        "   ✅ No pasar por charcos",
        "",
        "3. DIFERENCIAL:",
        "   ✅ Asegurar que hay diferencial en el cuadro",
        "   ✅ Mejor: usar diferencial portátil (30 mA)",
        "",
        "4. DESPUÉS DE USAR:",
        "   ✅ Recoger y guardar en lugar seco",
        "   ✅ Revisar el estado del cable",
        "",
        "❌ NUNCA usar alargadores de interior en exterior"
      ],
      "result": "Usar alargador certificado IP44+, con tierra, protegido de lluvia y con diferencial"
    }
  },
  {
    "id": "cuadro_electrico",
    "groupId": "prevencion_accidentes",
    "title": "Acceso al cuadro eléctrico",
    "enunciado": "¿Qué precauciones debes tomar al manipular el cuadro eléctrico?",
    "solution": {
      "steps": [
        "El cuadro eléctrico es una zona de alto riesgo:",
        "",
        "REGLAS BÁSICAS:",
        "",
        "1. SOLO PARA EMERGENCIAS:",
        "   • Bajar interruptores en caso de problema",
        "   • Subir interruptores que han saltado",
        "   • NO manipular cables ni conexiones",
        "",
        "2. ANTES DE TOCAR:",
        "   ✅ Manos completamente secas",
        "   ✅ No estar descalzo",
        "   ✅ No tocar partes metálicas",
        "   ✅ Usar solo los interruptores",
        "",
        "3. SI SALTA REPETIDAMENTE:",
        "   ❌ NO forzar el interruptor",
        "   ❌ NO puentear protecciones",
        "   ✅ Llamar a electricista",
        "   ✅ Hay un problema que debe resolverse",
        "",
        "4. MANTENIMIENTO:",
        "   • Probar el diferencial mensualmente (botón TEST)",
        "   • Revisar que no haya cables sueltos",
        "   • Mantener limpio y seco",
        "",
        "IMPORTANTE:",
        "Solo electricistas autorizados pueden abrir el cuadro",
        "y manipular las conexiones internas"
      ],
      "result": "Solo tocar interruptores, manos secas, no forzar, llamar electricista si hay problemas"
    }
  }
]
